impm/__init__.py
impm/__main__.py
impm/cli/__init__.py
impm/cli/cli.py
impm/cli/logging.py
impm-0.1.0.dist-info/WHEEL
impm-0.1.0.dist-info/METADATA
impm-0.1.0.dist-info/RECORD
